peeweext
tests
